reddit_account_generator/__init__.py
reddit_account_generator/_maker.py
reddit_account_generator/_verifier.py
reddit_account_generator/_version.py
reddit_account_generator/config.py
reddit_account_generator/exceptions.py
reddit_account_generator/proxies.py
reddit_account_generator/utils.py
reddit_account_generator-1.3.1.dist-info/LICENSE
reddit_account_generator-1.3.1.dist-info/METADATA
reddit_account_generator-1.3.1.dist-info/WHEEL
reddit_account_generator-1.3.1.dist-info/top_level.txt
reddit_account_generator-1.3.1.dist-info/RECORD
