Metadata-Version: 2.1
Name: reddit-account-generator
Version: 1.3.1
Summary: Automatic reddit account generator on selenium.
Home-page: https://github.com/cubicbyte/reddit-account-generator
Author: cubicbyte
Author-email: bmaruhnenko@gmail.com
License: MIT
Keywords: python reddit account-generator account-maker account-generation r-place rplace
Classifier: Development Status :: 5 - Production/Stable
Classifier: Programming Language :: Python :: 3
Classifier: Environment :: Console
Classifier: License :: OSI Approved :: MIT License
License-File: LICENSE
Requires-Dist: selenium <=4.9.1,>=4.7.0
Requires-Dist: selenium-recaptcha-solver <=1.9.0,>=1.4.0
Requires-Dist: random-username <=1.0.2,>=1.0.0
Requires-Dist: webdriverdownloader <=1.1.0.3,>=1.0.0
Requires-Dist: stem <=1.8.2,>=1.8.0
Requires-Dist: static-ffmpeg <=2.5,>=2.3
Requires-Dist: tempmail-python ==2.3.0
Requires-Dist: beautifulsoup4 ~=4.12.0
